{"nodes": [{"id": 0, "name": "DevRel Team", "category": "hub", "size": 30}, {"id": 1, "name": "Developer Advocates", "category": "member", "size": 20}, {"id": 2, "name": "Community Managers", "category": "member", "size": 20}, {"id": 3, "name": "Technical Writers", "category": "member", "size": 20}, {"id": 4, "name": "Developer Community", "category": "hub", "size": 30}, {"id": 5, "name": "Open Source Contributors", "category": "member", "size": 20}, {"id": 6, "name": "Enterprise Developers", "category": "member", "size": 20}, {"id": 7, "name": "Startup Developers", "category": "member", "size": 20}, {"id": 8, "name": "Content", "category": "hub", "size": 30}, {"id": 9, "name": "Documentation", "category": "member", "size": 20}, {"id": 10, "name": "Tutorials", "category": "member", "size": 20}, {"id": 11, "name": "Blog Posts", "category": "member", "size": 20}, {"id": 12, "name": "Video Content", "category": "member", "size": 20}, {"id": 13, "name": "Events", "category": "hub", "size": 30}, {"id": 14, "name": "Conferences", "category": "member", "size": 20}, {"id": 15, "name": "Meetups", "category": "member", "size": 20}, {"id": 16, "name": "Workshops", "category": "member", "size": 20}, {"id": 17, "name": "Hackathons", "category": "member", "size": 20}, {"id": 18, "name": "Platforms", "category": "hub", "size": 30}, {"id": 19, "name": "GitHub", "category": "member", "size": 20}, {"id": 20, "name": "Stack Overflow", "category": "member", "size": 20}, {"id": 21, "name": "Discord", "category": "member", "size": 20}, {"id": 22, "name": "Twitter", "category": "member", "size": 20}], "links": [{"source": 0, "target": 1, "value": 1}, {"source": 0, "target": 2, "value": 1}, {"source": 0, "target": 3, "value": 1}, {"source": 1, "target": 14, "value": 0.5}, {"source": 2, "target": 15, "value": 0.5}, {"source": 3, "target": 16, "value": 0.5}, {"source": 4, "target": 5, "value": 1}, {"source": 4, "target": 6, "value": 1}, {"source": 4, "target": 7, "value": 1}, {"source": 5, "target": 17, "value": 0.5}, {"source": 8, "target": 9, "value": 1}, {"source": 8, "target": 10, "value": 1}, {"source": 8, "target": 11, "value": 1}, {"source": 8, "target": 12, "value": 1}, {"source": 9, "target": 19, "value": 0.5}, {"source": 9, "target": 20, "value": 0.5}, {"source": 10, "target": 21, "value": 0.5}, {"source": 11, "target": 22, "value": 0.5}, {"source": 13, "target": 14, "value": 1}, {"source": 13, "target": 15, "value": 1}, {"source": 13, "target": 16, "value": 1}, {"source": 13, "target": 17, "value": 1}, {"source": 18, "target": 19, "value": 1}, {"source": 18, "target": 20, "value": 1}, {"source": 18, "target": 21, "value": 1}, {"source": 18, "target": 22, "value": 1}]}